setup.py
pyfunc/__init__.py
pyfunc/main.py
pyfunc/utils.py
pyfunc.egg-info/PKG-INFO
pyfunc.egg-info/SOURCES.txt
pyfunc.egg-info/dependency_links.txt
pyfunc.egg-info/entry_points.txt
pyfunc.egg-info/top_level.txt