Metadata-Version: 1.0
Name: pyfunc
Version: 0.1
Summary: Call python functions from your shell
Home-page: https://github.com/saurabh-hirani/pyfunc
Author: Saurabh Hirani
Author-email: saurabh.hirani@gmail.com
License: GPL v2
Platform: UNKNOWN
